Metadata-Version: 2.1
Name: hysteria
Version: 1.3.5.2
Summary: Python bindings for hysteria, a feature-packed proxy & relay tool.
Home-page: https://github.com/LorenEteval/hysteria-python
Author: Loren Eteval
Author-email: loren.eteval@proton.me
License: MIT
Classifier: Development Status :: 5 - Production/Stable
Classifier: License :: OSI Approved :: MIT License
Classifier: Intended Audience :: Developers
Classifier: Programming Language :: C++
Classifier: Programming Language :: Python :: 3
Classifier: Programming Language :: Python :: 3 :: Only
Classifier: Programming Language :: Python :: 3.8
Classifier: Programming Language :: Python :: 3.9
Classifier: Programming Language :: Python :: 3.10
Classifier: Programming Language :: Python :: 3.11
Classifier: Programming Language :: Python :: 3.10
Classifier: Programming Language :: Python :: 3.11
Classifier: Operating System :: OS Independent
Classifier: Topic :: Internet
Classifier: Topic :: Internet :: Proxy Servers
License-File: LICENSE
